node_require/__init__.py
node_require/bson_loader.py
node_require/json_loader.py
node_require/module_loader.py
node_require/req_impl.py
node_require/toml_loader.py
node_require/yaml_loader.py
node_require-2.0.1.dist-info/METADATA
node_require-2.0.1.dist-info/WHEEL
node_require-2.0.1.dist-info/top_level.txt
node_require-2.0.1.dist-info/RECORD
