Metadata-Version: 2.1
Name: node-require
Version: 2.0.1
Summary: Like Node.js's require(), but with more supported formats
Home-page: https://github.com/weerdy15/node-require
Author: weerdy15
License: MIT
Project-URL: Issue tracker, https://github.com/weerdy15/node-require/issues
Platform: UNKNOWN
Classifier: Development Status :: 5 - Production/Stable
Classifier: Intended Audience :: Developers
Classifier: Natural Language :: English
Classifier: Programming Language :: Python :: 3.9
Classifier: Programming Language :: Python :: 3.10
Classifier: Topic :: Utilities
Classifier: Typing :: Typed
Requires-Python: >=3.9.7
Provides-Extra: all_langs
Requires-Dist: toml ; extra == 'all_langs'
Requires-Dist: yaml ; extra == 'all_langs'
Requires-Dist: bson ; extra == 'all_langs'
Provides-Extra: bson
Requires-Dist: bson ; extra == 'bson'
Provides-Extra: toml
Requires-Dist: toml ; extra == 'toml'
Provides-Extra: yaml
Requires-Dist: yaml ; extra == 'yaml'
